{"version": "1", "message": "ERROR: Hidden Testcases server unreachable.", "problem_id": "ADS-1 remedial-5", "user_id": "shubhamsahu02", "score": {"sample": {"0": {"execution_time": 0.5986902713775635, "passed": false}, "1": {"execution_time": 0.6516969203948975, "passed": false}, "2": {"execution_time": 0.690704345703125, "passed": false}, "3": {"execution_time": 0.5681190490722656, "passed": false}, "4": {"execution_time": 0.517831563949585, "passed": false}, "5": {"execution_time": 0.6442444324493408, "passed": false}, "6": {"execution_time": 0.5435752868652344, "passed": false}}}, "check_style_score": "0/1"}